r00firmware/__init__.py
r00firmware/cli.py
r00firmware/firmware.py
r00firmware/main.py
r00firmware/helpers/__init__.py
r00firmware/helpers/exceptions.py
r00firmware-0.1.0.dist-info/METADATA
r00firmware-0.1.0.dist-info/WHEEL
r00firmware-0.1.0.dist-info/entry_points.txt
r00firmware-0.1.0.dist-info/RECORD
