Metadata-Version: 2.4
Name: r00firmware
Version: 0.1.0
Summary: Add your description here
Requires-Python: >=3.12
Requires-Dist: r00adb
Requires-Dist: r00dialoger
Requires-Dist: r00logger
Requires-Dist: r00system
